[
  {
    "id": "vol_1",
    "name": "Volunteer 1",
    "skills": [
      "Sanitation",
      "Electricity"
    ],
    "lat": 28.555714104103266,
    "lng": 77.16074604546624,
    "neighborhood": "Saket",
    "active": true
  },
  {
    "id": "vol_2",
    "name": "Volunteer 2",
    "skills": [
      "Health",
      "Water"
    ],
    "lat": 28.57208720312371,
    "lng": 77.18914830014648,
    "neighborhood": "Saket",
    "active": true
  },
  {
    "id": "vol_3",
    "name": "Volunteer 3",
    "skills": [
      "Health",
      "Electricity"
    ],
    "lat": 28.551986461316158,
    "lng": 77.11287342226733,
    "neighborhood": "Hauz Khas",
    "active": true
  },
  {
    "id": "vol_4",
    "name": "Volunteer 4",
    "skills": [
      "Water",
      "Electricity"
    ],
    "lat": 28.713463632971447,
    "lng": 77.14348130166384,
    "neighborhood": "Karol Bagh",
    "active": false
  },
  {
    "id": "vol_5",
    "name": "Volunteer 5",
    "skills": [
      "Water",
      "Sanitation"
    ],
    "lat": 28.670678003511508,
    "lng": 77.25428517758142,
    "neighborhood": "Janakpuri",
    "active": true
  },
  {
    "id": "vol_6",
    "name": "Volunteer 6",
    "skills": [
      "Water",
      "Sanitation"
    ],
    "lat": 28.67087968406931,
    "lng": 77.16520797692098,
    "neighborhood": "Rohini",
    "active": true
  },
  {
    "id": "vol_7",
    "name": "Volunteer 7",
    "skills": [
      "Roads",
      "Other"
    ],
    "lat": 28.521846730980645,
    "lng": 77.28901101602253,
    "neighborhood": "Dwarka",
    "active": true
  },
  {
    "id": "vol_8",
    "name": "Volunteer 8",
    "skills": [
      "Roads",
      "Health"
    ],
    "lat": 28.621140385583015,
    "lng": 77.10875266117768,
    "neighborhood": "Karol Bagh",
    "active": true
  },
  {
    "id": "vol_9",
    "name": "Volunteer 9",
    "skills": [
      "Health",
      "Water"
    ],
    "lat": 28.7071903379834,
    "lng": 77.25520854555124,
    "neighborhood": "Hauz Khas",
    "active": true
  },
  {
    "id": "vol_10",
    "name": "Volunteer 10",
    "skills": [
      "Health",
      "Other"
    ],
    "lat": 28.533508032083066,
    "lng": 77.24660457697024,
    "neighborhood": "Karol Bagh",
    "active": false
  },
  {
    "id": "vol_11",
    "name": "Volunteer 11",
    "skills": [
      "Roads",
      "Other"
    ],
    "lat": 28.725747880402093,
    "lng": 77.11368054189735,
    "neighborhood": "Dwarka",
    "active": false
  },
  {
    "id": "vol_12",
    "name": "Volunteer 12",
    "skills": [
      "Electricity",
      "Health"
    ],
    "lat": 28.622438543801856,
    "lng": 77.1956967928944,
    "neighborhood": "Karol Bagh",
    "active": true
  },
  {
    "id": "vol_13",
    "name": "Volunteer 13",
    "skills": [
      "Water",
      "Sanitation"
    ],
    "lat": 28.646048206760927,
    "lng": 77.17637806113484,
    "neighborhood": "Vasant Kunj",
    "active": true
  },
  {
    "id": "vol_14",
    "name": "Volunteer 14",
    "skills": [
      "Health",
      "Water"
    ],
    "lat": 28.568930484925986,
    "lng": 77.18038897395007,
    "neighborhood": "Rohini",
    "active": true
  },
  {
    "id": "vol_15",
    "name": "Volunteer 15",
    "skills": [
      "Roads",
      "Water"
    ],
    "lat": 28.634751646481526,
    "lng": 77.10214723243318,
    "neighborhood": "Rohini",
    "active": false
  },
  {
    "id": "vol_16",
    "name": "Volunteer 16",
    "skills": [
      "Sanitation",
      "Health"
    ],
    "lat": 28.595256279512242,
    "lng": 77.18139252096026,
    "neighborhood": "Janakpuri",
    "active": true
  },
  {
    "id": "vol_17",
    "name": "Volunteer 17",
    "skills": [
      "Water",
      "Other"
    ],
    "lat": 28.544972769389037,
    "lng": 77.21475729007355,
    "neighborhood": "Dwarka",
    "active": false
  },
  {
    "id": "vol_18",
    "name": "Volunteer 18",
    "skills": [
      "Water",
      "Other"
    ],
    "lat": 28.52846529717836,
    "lng": 77.2210731708358,
    "neighborhood": "Vasant Kunj",
    "active": true
  },
  {
    "id": "vol_19",
    "name": "Volunteer 19",
    "skills": [
      "Roads",
      "Water"
    ],
    "lat": 28.5604510149376,
    "lng": 77.22290762122891,
    "neighborhood": "Janakpuri",
    "active": false
  },
  {
    "id": "vol_20",
    "name": "Volunteer 20",
    "skills": [
      "Other",
      "Roads"
    ],
    "lat": 28.664280967352134,
    "lng": 77.1316349864607,
    "neighborhood": "Saket",
    "active": true
  },
  {
    "id": "vol_21",
    "name": "Volunteer 21",
    "skills": [
      "Health",
      "Roads"
    ],
    "lat": 28.639953122693527,
    "lng": 77.18549752270302,
    "neighborhood": "Lajpat Nagar",
    "active": true
  },
  {
    "id": "vol_22",
    "name": "Volunteer 22",
    "skills": [
      "Health",
      "Roads"
    ],
    "lat": 28.724309370226624,
    "lng": 77.1726223277103,
    "neighborhood": "Janakpuri",
    "active": true
  },
  {
    "id": "vol_23",
    "name": "Volunteer 23",
    "skills": [
      "Health",
      "Roads"
    ],
    "lat": 28.65292153916851,
    "lng": 77.21130262499574,
    "neighborhood": "Hauz Khas",
    "active": true
  },
  {
    "id": "vol_24",
    "name": "Volunteer 24",
    "skills": [
      "Sanitation",
      "Health"
    ],
    "lat": 28.61935681305196,
    "lng": 77.10755746522469,
    "neighborhood": "Rohini",
    "active": true
  },
  {
    "id": "vol_25",
    "name": "Volunteer 25",
    "skills": [
      "Sanitation",
      "Water"
    ],
    "lat": 28.54173803858848,
    "lng": 77.24667872779804,
    "neighborhood": "Karol Bagh",
    "active": true
  },
  {
    "id": "vol_26",
    "name": "Volunteer 26",
    "skills": [
      "Roads",
      "Electricity"
    ],
    "lat": 28.71333803580309,
    "lng": 77.25191491702799,
    "neighborhood": "Dwarka",
    "active": true
  },
  {
    "id": "vol_27",
    "name": "Volunteer 27",
    "skills": [
      "Roads",
      "Electricity"
    ],
    "lat": 28.599179212998784,
    "lng": 77.194947943925,
    "neighborhood": "Dwarka",
    "active": true
  },
  {
    "id": "vol_28",
    "name": "Volunteer 28",
    "skills": [
      "Roads",
      "Electricity"
    ],
    "lat": 28.748694282692806,
    "lng": 77.17788700226299,
    "neighborhood": "Dwarka",
    "active": true
  },
  {
    "id": "vol_29",
    "name": "Volunteer 29",
    "skills": [
      "Roads",
      "Health"
    ],
    "lat": 28.5237371892381,
    "lng": 77.17457600092288,
    "neighborhood": "Dwarka",
    "active": true
  },
  {
    "id": "vol_30",
    "name": "Volunteer 30",
    "skills": [
      "Roads",
      "Health"
    ],
    "lat": 28.547444434850302,
    "lng": 77.10834360409336,
    "neighborhood": "Karol Bagh",
    "active": false
  },
  {
    "id": "vol_31",
    "name": "Volunteer 31",
    "skills": [
      "Electricity",
      "Other"
    ],
    "lat": 28.56538507407549,
    "lng": 77.23387474983352,
    "neighborhood": "Rohini",
    "active": true
  },
  {
    "id": "vol_32",
    "name": "Volunteer 32",
    "skills": [
      "Health",
      "Roads"
    ],
    "lat": 28.699037384625093,
    "lng": 77.20149970767869,
    "neighborhood": "Karol Bagh",
    "active": true
  },
  {
    "id": "vol_33",
    "name": "Volunteer 33",
    "skills": [
      "Other",
      "Electricity"
    ],
    "lat": 28.61660782086295,
    "lng": 77.26430401749127,
    "neighborhood": "Dwarka",
    "active": true
  },
  {
    "id": "vol_34",
    "name": "Volunteer 34",
    "skills": [
      "Other",
      "Electricity"
    ],
    "lat": 28.675974259449603,
    "lng": 77.18589753817098,
    "neighborhood": "Rohini",
    "active": false
  },
  {
    "id": "vol_35",
    "name": "Volunteer 35",
    "skills": [
      "Electricity",
      "Water"
    ],
    "lat": 28.691513335001304,
    "lng": 77.28980701428172,
    "neighborhood": "Rohini",
    "active": true
  },
  {
    "id": "vol_36",
    "name": "Volunteer 36",
    "skills": [
      "Electricity",
      "Roads"
    ],
    "lat": 28.663748386433678,
    "lng": 77.14404916371113,
    "neighborhood": "Dwarka",
    "active": true
  },
  {
    "id": "vol_37",
    "name": "Volunteer 37",
    "skills": [
      "Sanitation",
      "Roads"
    ],
    "lat": 28.59729035848659,
    "lng": 77.11740496944414,
    "neighborhood": "Vasant Kunj",
    "active": true
  },
  {
    "id": "vol_38",
    "name": "Volunteer 38",
    "skills": [
      "Roads",
      "Water"
    ],
    "lat": 28.54699116529549,
    "lng": 77.18928035006829,
    "neighborhood": "Hauz Khas",
    "active": false
  },
  {
    "id": "vol_39",
    "name": "Volunteer 39",
    "skills": [
      "Roads",
      "Other"
    ],
    "lat": 28.74791551787845,
    "lng": 77.11594848201874,
    "neighborhood": "Rohini",
    "active": true
  },
  {
    "id": "vol_40",
    "name": "Volunteer 40",
    "skills": [
      "Electricity",
      "Sanitation"
    ],
    "lat": 28.64742430463855,
    "lng": 77.10668039095685,
    "neighborhood": "Saket",
    "active": false
  },
  {
    "id": "vol_41",
    "name": "Volunteer 41",
    "skills": [
      "Other",
      "Roads"
    ],
    "lat": 28.690521206897124,
    "lng": 77.28873496302715,
    "neighborhood": "Karol Bagh",
    "active": true
  },
  {
    "id": "vol_42",
    "name": "Volunteer 42",
    "skills": [
      "Water",
      "Health"
    ],
    "lat": 28.746257937087464,
    "lng": 77.21624179592378,
    "neighborhood": "Saket",
    "active": true
  },
  {
    "id": "vol_43",
    "name": "Volunteer 43",
    "skills": [
      "Health",
      "Sanitation"
    ],
    "lat": 28.604847346803385,
    "lng": 77.25518395174284,
    "neighborhood": "Saket",
    "active": false
  },
  {
    "id": "vol_44",
    "name": "Volunteer 44",
    "skills": [
      "Roads",
      "Sanitation"
    ],
    "lat": 28.66903633198492,
    "lng": 77.28378046452524,
    "neighborhood": "Karol Bagh",
    "active": true
  },
  {
    "id": "vol_45",
    "name": "Volunteer 45",
    "skills": [
      "Other",
      "Water"
    ],
    "lat": 28.512282388258352,
    "lng": 77.22753123112048,
    "neighborhood": "Hauz Khas",
    "active": true
  },
  {
    "id": "vol_46",
    "name": "Volunteer 46",
    "skills": [
      "Electricity",
      "Other"
    ],
    "lat": 28.57751425514109,
    "lng": 77.27960602420315,
    "neighborhood": "Janakpuri",
    "active": true
  },
  {
    "id": "vol_47",
    "name": "Volunteer 47",
    "skills": [
      "Electricity",
      "Other"
    ],
    "lat": 28.731516849611896,
    "lng": 77.29712606561517,
    "neighborhood": "Dwarka",
    "active": true
  },
  {
    "id": "vol_48",
    "name": "Volunteer 48",
    "skills": [
      "Water",
      "Health"
    ],
    "lat": 28.511218085958976,
    "lng": 77.20664199729092,
    "neighborhood": "Rohini",
    "active": true
  },
  {
    "id": "vol_49",
    "name": "Volunteer 49",
    "skills": [
      "Electricity",
      "Health"
    ],
    "lat": 28.5195121523418,
    "lng": 77.28684794913987,
    "neighborhood": "Karol Bagh",
    "active": false
  },
  {
    "id": "vol_50",
    "name": "Volunteer 50",
    "skills": [
      "Electricity",
      "Health"
    ],
    "lat": 28.644504212667908,
    "lng": 77.28821106097784,
    "neighborhood": "Lajpat Nagar",
    "active": true
  }
]